{
	"basenames": {
		"readme": "Readme.md",
		"六要素数据工程软件化材料提供.docx": "六要素数据工程软件化材料提供.docx",
		"唯格勒当雄冰川": "data/研究对象/冰川/唯格勒当雄冰川.md",
		"克亚吉尔冰川": "data/研究对象/冰川/克亚吉尔冰川.md",
		"遥感影像": "data/相关数据/遥感影像.md",
		"时序遥感图像": "data/相关数据/时序遥感图像.md",
		"气象数据": "data/相关数据/气象数据.md",
		"站点数据": "data/相关数据/站点数据.md",
		"微波影像": "data/相关数据/微波影像.md",
		"微波干涉影像": "data/相关数据/微波干涉影像.md",
		"水文数据": "data/相关数据/水文数据.md",
		"全色影像": "data/相关数据/全色影像.md",
		"红外影像": "data/相关数据/红外影像.md",
		"光学立体影像": "data/相关数据/光学立体影像.md",
		"高光谱影像": "data/相关数据/高光谱影像.md",
		"高程影像": "data/相关数据/高程影像.md",
		"多光谱影像": "data/相关数据/多光谱影像.md",
		"滑坡体土壤含水率": "data/特征/冻融滑坡特征/滑坡体土壤含水率.md",
		"滑坡体几何形态": "data/特征/冻融滑坡特征/滑坡体几何形态.md",
		"滑坡体地下形变": "data/特征/冻融滑坡特征/滑坡体地下形变.md",
		"滑坡体地表形变": "data/特征/冻融滑坡特征/滑坡体地表形变.md",
		"与其他湖的水力联系": "data/特征/冰湖溃决特征/与其他湖的水力联系.md",
		"输入·输出水量": "data/特征/冰湖溃决特征/输入·输出水量.md",
		"气象要素": "data/特征/冰湖溃决特征/气象要素.md",
		"集水面积": "data/特征/冰湖溃决特征/集水面积.md",
		"湖面温度": "data/特征/冰湖溃决特征/湖面温度.md",
		"关联冰川及其变化": "data/特征/冰湖溃决特征/关联冰川及其变化.md",
		"冰湖水位及其变化": "data/特征/冰湖溃决特征/冰湖水位及其变化.md",
		"冰湖面积及其变化": "data/特征/冰湖溃决特征/冰湖面积及其变化.md",
		"冰湖溃决洪水过程": "data/特征/冰湖溃决特征/冰湖溃决洪水过程.md",
		"冰湖库容、储水量及其变化": "data/特征/冰湖溃决特征/冰湖库容、储水量及其变化.md",
		"冰湖湖底地形": "data/特征/冰湖溃决特征/冰湖湖底地形.md",
		"冰湖坝体厚度和高度": "data/特征/冰湖溃决特征/冰湖坝体厚度和高度.md",
		"微波散射特征": "data/特征/冰川跃动特征/微波散射特征.md",
		"微波极化特征": "data/特征/冰川跃动特征/微波极化特征.md",
		"光谱特征": "data/特征/冰川跃动特征/光谱特征.md",
		"冰川渗透水量": "data/特征/冰川跃动特征/冰川渗透水量.md",
		"冰川融水和冰碛物": "data/特征/冰川跃动特征/冰川融水和冰碛物.md",
		"冰川前缘位置": "data/特征/冰川跃动特征/冰川前缘位置.md",
		"冰川面积和厚度": "data/特征/冰川跃动特征/冰川面积和厚度.md",
		"冰川湖": "data/特征/冰川跃动特征/冰川湖.md",
		"冰川表面流速": "data/特征/冰川跃动特征/冰川表面流速.md",
		"冰川表面径流": "data/特征/冰川跃动特征/冰川表面径流.md",
		"库容-面积计算公式": "data/方法/库容-面积计算公式.md",
		"激光测高": "data/方法/激光测高.md",
		"多光谱遥感反演": "data/方法/多光谱遥感反演.md",
		"gnss原位监测": "data/方法/GNSS原位监测.md",
		"形变检测": "data/方法/形变检测.md",
		"物质平衡法": "data/方法/物质平衡法.md",
		"纹理法": "data/方法/纹理法.md",
		"特征学习法": "data/方法/特征学习法.md",
		"随机森林": "data/方法/随机森林.md",
		"水渗透解析单元方法": "data/方法/水渗透解析单元方法.md",
		"水层渗透系数经验公式": "data/方法/水层渗透系数经验公式.md",
		"时序微分": "data/方法/时序微分.md",
		"散射系数反演": "data/方法/散射系数反演.md",
		"散射系数·角度分析": "data/方法/散射系数·角度分析.md",
		"极化分解法": "data/方法/极化分解法.md",
		"归一化差值": "data/方法/归一化差值.md",
		"光学影像偏移量追踪": "data/方法/光学影像偏移量追踪.md",
		"高程变化检测": "data/方法/高程变化检测.md",
		"层流理论算法": "data/方法/层流理论算法.md",
		"波段法": "data/方法/波段法.md",
		"波段差分": "data/方法/波段差分.md",
		"波段比值": "data/方法/波段比值.md",
		"ramms演进法": "data/方法/RAMMS演进法.md",
		"cnn": "data/方法/CNN.md",
		"冰湖溃决": "data/目录/三级目录/冰湖溃决.md",
		"冰川跃动": "data/目录/三级目录/冰川跃动.md",
		"冰川演变": "data/目录/二级目录/冰川演变.md",
		"冰川速变": "data/目录/二级目录/冰川速变.md",
		"冻融滑坡": "data/目录/二级目录/冻融滑坡.md",
		"冻土": "data/目录/一级目录/冻土.md",
		"冰川": "data/目录/一级目录/冰川.md",
		"file-index.json": "file-index.json",
		"r-c.jpg": "Attachment/R-C.jpg",
		"picture.png": "Attachment/Picture.png"
	},
	"paths": [
		"Attachment/Picture.png",
		"Attachment/R-C.jpg",
		"Readme.md",
		"data/方法/CNN.md",
		"data/方法/GNSS原位监测.md",
		"data/方法/RAMMS演进法.md",
		"data/方法/光学影像偏移量追踪.md",
		"data/方法/多光谱遥感反演.md",
		"data/方法/层流理论算法.md",
		"data/方法/库容-面积计算公式.md",
		"data/方法/归一化差值.md",
		"data/方法/形变检测.md",
		"data/方法/散射系数·角度分析.md",
		"data/方法/散射系数反演.md",
		"data/方法/时序微分.md",
		"data/方法/极化分解法.md",
		"data/方法/水层渗透系数经验公式.md",
		"data/方法/水渗透解析单元方法.md",
		"data/方法/波段差分.md",
		"data/方法/波段比值.md",
		"data/方法/波段法.md",
		"data/方法/激光测高.md",
		"data/方法/物质平衡法.md",
		"data/方法/特征学习法.md",
		"data/方法/纹理法.md",
		"data/方法/随机森林.md",
		"data/方法/高程变化检测.md",
		"data/特征/冰川跃动特征/光谱特征.md",
		"data/特征/冰川跃动特征/冰川前缘位置.md",
		"data/特征/冰川跃动特征/冰川渗透水量.md",
		"data/特征/冰川跃动特征/冰川湖.md",
		"data/特征/冰川跃动特征/冰川融水和冰碛物.md",
		"data/特征/冰川跃动特征/冰川表面径流.md",
		"data/特征/冰川跃动特征/冰川表面流速.md",
		"data/特征/冰川跃动特征/冰川面积和厚度.md",
		"data/特征/冰川跃动特征/微波散射特征.md",
		"data/特征/冰川跃动特征/微波极化特征.md",
		"data/特征/冰湖溃决特征/与其他湖的水力联系.md",
		"data/特征/冰湖溃决特征/关联冰川及其变化.md",
		"data/特征/冰湖溃决特征/冰湖坝体厚度和高度.md",
		"data/特征/冰湖溃决特征/冰湖库容、储水量及其变化.md",
		"data/特征/冰湖溃决特征/冰湖水位及其变化.md",
		"data/特征/冰湖溃决特征/冰湖湖底地形.md",
		"data/特征/冰湖溃决特征/冰湖溃决洪水过程.md",
		"data/特征/冰湖溃决特征/冰湖面积及其变化.md",
		"data/特征/冰湖溃决特征/气象要素.md",
		"data/特征/冰湖溃决特征/湖面温度.md",
		"data/特征/冰湖溃决特征/输入·输出水量.md",
		"data/特征/冰湖溃决特征/集水面积.md",
		"data/特征/冻融滑坡特征/滑坡体几何形态.md",
		"data/特征/冻融滑坡特征/滑坡体土壤含水率.md",
		"data/特征/冻融滑坡特征/滑坡体地下形变.md",
		"data/特征/冻融滑坡特征/滑坡体地表形变.md",
		"data/目录/一级目录/冰川.md",
		"data/目录/一级目录/冻土.md",
		"data/目录/三级目录/冰川跃动.md",
		"data/目录/三级目录/冰湖溃决.md",
		"data/目录/二级目录/冰川演变.md",
		"data/目录/二级目录/冰川速变.md",
		"data/目录/二级目录/冻融滑坡.md",
		"data/相关数据/光学立体影像.md",
		"data/相关数据/全色影像.md",
		"data/相关数据/多光谱影像.md",
		"data/相关数据/微波干涉影像.md",
		"data/相关数据/微波影像.md",
		"data/相关数据/时序遥感图像.md",
		"data/相关数据/气象数据.md",
		"data/相关数据/水文数据.md",
		"data/相关数据/站点数据.md",
		"data/相关数据/红外影像.md",
		"data/相关数据/遥感影像.md",
		"data/相关数据/高光谱影像.md",
		"data/相关数据/高程影像.md",
		"data/研究对象/冰川/克亚吉尔冰川.md",
		"data/研究对象/冰川/唯格勒当雄冰川.md",
		"file-index.json",
		"六要素数据工程软件化材料提供.docx"
	]
}